package/__init__.py
package/myLib.py
meupacote-0.0.1.dist-info/METADATA
meupacote-0.0.1.dist-info/WHEEL
meupacote-0.0.1.dist-info/entry_points.txt
meupacote-0.0.1.dist-info/top_level.txt
meupacote-0.0.1.dist-info/RECORD
